Destiny/__init__.py
Destiny/api.py
Destiny_API_FFCoder-1.1.dist-info/LICENSE
Destiny_API_FFCoder-1.1.dist-info/METADATA
Destiny_API_FFCoder-1.1.dist-info/WHEEL
Destiny_API_FFCoder-1.1.dist-info/top_level.txt
Destiny_API_FFCoder-1.1.dist-info/RECORD
