Metadata-Version: 2.1
Name: Destiny-API-FFCoder
Version: 1.1
Summary: A WIP Destiny Library Systems API
Home-page: https://github.com/FFCoder/DestinyAPI
Author: Jonathon Chambers
Author-email: me@jonathonchambers.com
License: UNKNOWN
Project-URL: Bug Tracker, https://github.com/FFCoder/DestinyAPI/issues
Platform: UNKNOWN
Classifier: Programming Language :: Python :: 3
Classifier: License :: OSI Approved :: MIT License
Classifier: Operating System :: OS Independent
Requires-Python: >=3.6
License-File: LICENSE
Requires-Dist: bs4
Requires-Dist: requests
